openapi2callables-0.1.1.dist-info/METADATA
openapi2callables-0.1.1.dist-info/WHEEL
openapi2callables-0.1.1.dist-info/entry_points.txt
openapi2callables-0.1.1.dist-info/licenses/LICENSE
openapi2callables/__init__.py
openapi2callables/cli.py
openapi2callables/parse.py
openapi2callables/server.py
openapi2callables/tools.py
openapi2callables-0.1.1.dist-info/RECORD
