Metadata-Version: 2.1
Name: openapi2callables
Version: 0.1.1
Summary: Parse and project OpenAPI endpoints into OpenAI/GenericLLM compatible Tools
Keywords: openapi,fastapi,api,llm,tools,openai
Author-Email: Andrew Bolster <andrew.bolster@gmail.com>
License: MIT License
Classifier: Development Status :: 4 - Beta
Classifier: Intended Audience :: Developers
Classifier: License :: OSI Approved :: MIT License
Classifier: Programming Language :: Python :: 3
Classifier: Programming Language :: Python :: 3.10
Classifier: Programming Language :: Python :: 3.11
Classifier: Programming Language :: Python :: 3.12
Classifier: Programming Language :: Python :: 3.13
Classifier: Topic :: Software Development :: Libraries
Classifier: Topic :: Software Development :: Libraries :: Python Modules
Classifier: Topic :: Internet :: WWW/HTTP :: WSGI :: Application
Classifier: Topic :: Software Development :: Code Generators
Project-URL: Homepage, https://github.com/andrewbolster/openapi2callables
Project-URL: Documentation, https://openapi2callables.readthedocs.io
Project-URL: Repository, https://github.com/andrewbolster/openapi2callables.git
Project-URL: Bug Tracker, https://github.com/andrewbolster/openapi2callables/issues
Requires-Python: <4.0,>=3.10
Requires-Dist: fastapi<1.0.0,>=0.115.8
Requires-Dist: requests<3.0.0,>=2.32.3
Requires-Dist: jsonref<2.0.0,>=1.1.0
Requires-Dist: uvicorn<1.0.0,>=0.34.0
Requires-Dist: pyyaml<7.0,>=6.0
Requires-Dist: click<9.0.0,>=8.0.0
Requires-Dist: pydantic[email]>=2.10.6
